{"col": 10, "value": "7.75", "left": {"col": 6, "value": "", "left": "Q", "right": {"col": 0, "value": "776", "left": "S", "right": {"col": 0, "value": "142", "left": "S", "right": {"col": 0, "value": "407", "left": "S", "right": "Q"}}}}, "right": {"col": 2, "value": "1", "left": {"col": 3, "value": "\"Minahan", "left": "Q", "right": {"col": 9, "value": "113572", "left": "", "right": {"col": 10, "value": "26.55", "left": "S", "right": "S"}}}, "right": {"col": 10, "value": "7.2292", "left": "C", "right": {"col": 6, "value": "", "left": {"col": 10, "value": "7.225", "left": "C", "right": "S"}, "right": {"col": 3, "value": "\"Rice", "left": "Q", "right": "S"}}}}}